pwlf/__init__.py
pwlf/pwlf.py
pwlf/version.py
pwlf-2.5.1.dist-info/LICENSE
pwlf-2.5.1.dist-info/METADATA
pwlf-2.5.1.dist-info/WHEEL
pwlf-2.5.1.dist-info/top_level.txt
pwlf-2.5.1.dist-info/RECORD
