Metadata-Version: 2.2
Name: pwlf
Version: 2.5.1
Summary: fit piecewise linear functions to data
Home-page: https://github.com/cjekel/piecewise_linear_fit_py
Author: Charles Jekel
Author-email: cjekel@gmail.com
License: MIT License
Platform: any
Classifier: License :: OSI Approved :: MIT License
Classifier: Programming Language :: Python :: 3
Requires-Python: >3.5
License-File: LICENSE
Requires-Dist: numpy>=1.14.0
Requires-Dist: scipy>=1.8.0
Dynamic: author
Dynamic: author-email
Dynamic: classifier
Dynamic: description
Dynamic: home-page
Dynamic: license
Dynamic: platform
Dynamic: requires-dist
Dynamic: requires-python
Dynamic: summary
